gemini_builder/__init__.py
gemini_builder-0.1.0.dist-info/LICENSE.txt
gemini_builder-0.1.0.dist-info/METADATA
gemini_builder-0.1.0.dist-info/WHEEL
gemini_builder-0.1.0.dist-info/top_level.txt
gemini_builder-0.1.0.dist-info/zip-safe
gemini_builder-0.1.0.dist-info/RECORD
