Metadata-Version: 2.1
Name: gemini-builder
Version: 0.1.0
Summary: Build text/gemini files from Python
Home-page: UNKNOWN
Author: Martin Ibert
Author-email: python@maribert.info
License: MIT
Platform: UNKNOWN
Classifier: Development Status :: 3 - Alpha
Classifier: Intended Audience :: Developers
Classifier: Programming Language :: Python :: 3
Classifier: License :: OSI Approved :: MIT License
Classifier: Operating System :: OS Independent
Requires-Python: >=3.7
